{
  "config": {
    "title": "Class101",
    "description": "My awesome app using docz",
    "themeConfig": {},
    "ordering": "descending",
    "version": "0.11.0",
    "repository": null
  },
  "entries": {
    "src/index.mdx": {
      "menu": "Class101 UI",
      "name": "Quick Start",
      "route": "/",
      "id": "6576455a124f9aaefd860597f03a8fe4",
      "filepath": "src/index.mdx",
      "link": null,
      "slug": "src-index",
      "order": 0,
      "headings": [
        {
          "depth": 1,
          "slug": "class101-ui",
          "value": "Class101 ui"
        },
        {
          "depth": 1,
          "slug": "quick-start",
          "value": "Quick start"
        },
        {
          "depth": 2,
          "slug": "install",
          "value": "Install"
        },
        {
          "depth": 2,
          "slug": "usage",
          "value": "Usage"
        }
      ]
    },
    "src/cores/ProgressBar.mdx": {
      "menu": "Core",
      "name": "Progress bar",
      "route": "/cores",
      "id": "f2a95769529f849d413344fe2d58d37d",
      "filepath": "src/cores/ProgressBar.mdx",
      "link": null,
      "slug": "src-cores-progress-bar",
      "order": 0,
      "headings": [
        {
          "depth": 1,
          "slug": "spinner",
          "value": "Spinner"
        },
        {
          "depth": 2,
          "slug": "props",
          "value": "Props"
        },
        {
          "depth": 2,
          "slug": "basic-usage",
          "value": "Basic usage"
        },
        {
          "depth": 2,
          "slug": "custom-example",
          "value": "Custom example"
        }
      ]
    },
    "src/cores/Spinner.mdx": {
      "menu": "Core",
      "name": "Spinner",
      "route": "/cores",
      "id": "2ce1a5a4a37a3b063387663edb4d3028",
      "filepath": "src/cores/Spinner.mdx",
      "link": null,
      "slug": "src-cores-spinner",
      "order": 0,
      "headings": [
        {
          "depth": 1,
          "slug": "spinner",
          "value": "Spinner"
        },
        {
          "depth": 2,
          "slug": "props",
          "value": "Props"
        },
        {
          "depth": 2,
          "slug": "basic-usage",
          "value": "Basic usage"
        },
        {
          "depth": 2,
          "slug": "custom-example",
          "value": "Custom example"
        }
      ]
    }
  }
}